stvpoll/__init__.py
stvpoll/abcs.py
stvpoll/cpo_stv.py
stvpoll/exceptions.py
stvpoll/irv.py
stvpoll/quotas.py
stvpoll/result.py
stvpoll/scottish_stv.py
stvpoll/tiebreak_strategies.py
stvpoll/transfer_strategies.py
stvpoll/types.py
stvpoll/utils.py
stvpoll-0.4.6.dist-info/METADATA
stvpoll-0.4.6.dist-info/WHEEL
stvpoll-0.4.6.dist-info/top_level.txt
stvpoll-0.4.6.dist-info/RECORD
