Metadata-Version: 2.4
Name: STVPoll
Version: 0.4.6
Summary: STV polling methods
Home-page: https://github.com/VoteIT/STVPoll
Author: Johan Schiff & Betahaus development team
Author-email: johan@betahaus.net
License: GPLv3
Keywords: election poll stv
Classifier: Development Status :: 4 - Beta
Classifier: License :: OSI Approved :: GNU General Public License v3 or later (GPLv3+)
Classifier: Operating System :: OS Independent
Classifier: Programming Language :: Python
Classifier: Programming Language :: Python :: 3
Classifier: Programming Language :: Python :: 3 :: Only
Requires-Dist: tarjan>=0.2
Provides-Extra: testing
Requires-Dist: coverage>=7.2; extra == "testing"
